wagtail_newsletter_django_backend/__init__.py
wagtail_newsletter_django_backend/admin.py
wagtail_newsletter_django_backend/admin_viewsets.py
wagtail_newsletter_django_backend/apps.py
wagtail_newsletter_django_backend/campaign_backend.py
wagtail_newsletter_django_backend/forms.py
wagtail_newsletter_django_backend/models.py
wagtail_newsletter_django_backend/tests.py
wagtail_newsletter_django_backend/urls.py
wagtail_newsletter_django_backend/views.py
wagtail_newsletter_django_backend/wagtail_hooks.py
wagtail_newsletter_django_backend/management/__init__.py
wagtail_newsletter_django_backend/management/commands/__init__.py
wagtail_newsletter_django_backend/management/commands/send_scheduled_campaigns.py
wagtail_newsletter_django_backend/migrations/0001_initial.py
wagtail_newsletter_django_backend/migrations/0002_alter_audience_name_alter_audiencesegment_name_and_more.py
wagtail_newsletter_django_backend/migrations/0003_alter_campaign_audience_segment.py
wagtail_newsletter_django_backend/migrations/__init__.py
wagtail_newsletter_django_backend/templates/wagtail_newsletter_django_backend/manage.html
wagtail_newsletter_django_backend/templates/wagtail_newsletter_django_backend/manage_tag.html
wagtail_newsletter_django_backend/templates/wagtail_newsletter_django_backend/unsubscribe.html
wagtail_newsletter_django_backend/templates/wagtail_newsletter_django_backend/unsubscribe_tag.html
wagtail_newsletter_django_backend/templatetags/__init__.py
wagtail_newsletter_django_backend/templatetags/wagtail_newsletter_django_backend_tags.py
wagtail_newsletter_django_backend-0.5.9.dist-info/licenses/LICENSE
wagtail_newsletter_django_backend-0.5.9.dist-info/WHEEL
wagtail_newsletter_django_backend-0.5.9.dist-info/METADATA
wagtail_newsletter_django_backend-0.5.9.dist-info/RECORD
