Metadata-Version: 2.4
Name: wagtail-newsletter-django-backend
Version: 0.5.9
Summary: An internal Django backend to wagtail-newsletter.
Author-email: "Taylor C. Richberger" <taylor@axfive.net>
Maintainer-email: "Taylor C. Richberger" <taylor@axfive.net>
Requires-Python: >= 3.10
License-File: LICENSE
Requires-Dist: Django >=5.2, <5.3
Requires-Dist: wagtail >=7.1, <7.3
Requires-Dist: wagtail-newsletter >=0.2.2, <0.2.4
Requires-Dist: html2text >= 2025.4.15
Project-URL: documentation, https://wagtail-newsletter-django-backend.readthedocs.io/en/latest/
Project-URL: repository, https://forge.axfive.net/Taylor/wagtail-newsletter-django-backend
